[
	{"suit":"clubs","rang":"Ace"},
	{"suit":"clubs","rang":"2"},
	{"suit":"clubs","rang":"3"},
	{"suit":"clubs","rang":"4"},
	{"suit":"clubs","rang":"5"},
	{"suit":"clubs","rang":"6"},
	{"suit":"clubs","rang":"7"},
	{"suit":"clubs","rang":"8"},
	{"suit":"clubs","rang":"9"},
	{"suit":"clubs","rang":"10"},
	{"suit":"clubs","rang":"Jack"},
	{"suit":"clubs","rang":"Queen"},
	{"suit":"clubs","rang":"King"},
	{"suit":"diamonds","rang":"Ace"},
	{"suit":"diamonds","rang":"2"},
	{"suit":"diamonds","rang":"3"},
	{"suit":"diamonds","rang":"4"},
	{"suit":"diamonds","rang":"5"},
	{"suit":"diamonds","rang":"6"},
	{"suit":"diamonds","rang":"7"},
	{"suit":"diamonds","rang":"8"},
	{"suit":"diamonds","rang":"9"},
	{"suit":"diamonds","rang":"10"},
	{"suit":"diamonds","rang":"Jack"},
	{"suit":"diamonds","rang":"Queen"},
	{"suit":"diamonds","rang":"King"},
	{"suit":"hearts","rang":"Ace"},
	{"suit":"hearts","rang":"2"},
	{"suit":"hearts","rang":"3"},
	{"suit":"hearts","rang":"4"},
	{"suit":"hearts","rang":"5"},
	{"suit":"hearts","rang":"6"},
	{"suit":"hearts","rang":"7"},
	{"suit":"hearts","rang":"8"},
	{"suit":"hearts","rang":"9"},
	{"suit":"hearts","rang":"10"},
	{"suit":"hearts","rang":"Jack"},
	{"suit":"hearts","rang":"Queen"},
	{"suit":"hearts","rang":"King"},
	{"suit":"spades","rang":"Ace"},
	{"suit":"spades","rang":"2"},
	{"suit":"spades","rang":"3"},
	{"suit":"spades","rang":"4"},
	{"suit":"spades","rang":"5"},
	{"suit":"spades","rang":"6"},
	{"suit":"spades","rang":"7"},
	{"suit":"spades","rang":"8"},
	{"suit":"spades","rang":"9"},
	{"suit":"spades","rang":"10"},
	{"suit":"spades","rang":"Jack"},
	{"suit":"spades","rang":"Queen"},
	{"suit":"spades","rang":"King"}
]